miplib/__init__.py
miplib/analysis/__init__.py
miplib/analysis/calculate.py
miplib/analysis/image_quality/__init__.py
miplib/analysis/image_quality/filters.py
miplib/analysis/image_quality/image_quality_ranking.py
miplib/analysis/image_quality/utils.py
miplib/analysis/resolution/__init__.py
miplib/analysis/resolution/analysis.py
miplib/analysis/resolution/fourier_ring_correlation.py
miplib/analysis/resolution/fourier_shell_correlation.py
miplib/analysis/resolution/test/__init__.py
miplib/analysis/resolution/test/test_iterators.py
miplib/bin/__init__.py
miplib/bin/correlatem.py
miplib/bin/fuse.py
miplib/bin/import.py
miplib/bin/ism.py
miplib/bin/power.py
miplib/bin/pyimq.py
miplib/bin/register.py
miplib/bin/resolution.py
miplib/bin/subjective.py
miplib/data/__init__.py
miplib/data/definitions.py
miplib/data/containers/__init__.py
miplib/data/containers/array_detector_data.py
miplib/data/containers/fourier_correlation_data.py
miplib/data/containers/image.py
miplib/data/containers/image_data.py
miplib/data/containers/temp_data.py
miplib/data/converters/__init__.py
miplib/data/converters/conv_array_detector_data.py
miplib/data/coordinates/__init__.py
miplib/data/coordinates/polar.py
miplib/data/core/__init__.py
miplib/data/core/dictionary.py
miplib/data/core/tests/__init__.py
miplib/data/core/tests/test_fixedDictionary.py
miplib/data/io/__init__.py
miplib/data/io/_tifffile.cpython-36m-darwin.so
miplib/data/io/array_detector_data.py
miplib/data/io/fourier_correlation_data_reader.py
miplib/data/io/fourier_correlation_data_writer.py
miplib/data/io/read.py
miplib/data/io/tiffile.py
miplib/data/io/write.py
miplib/data/io/tests/__init__.py
miplib/data/io/tests/test_fourierCorrelationDataIO.py
miplib/data/iterators/__init__.py
miplib/data/iterators/fourier_ring_iterators.py
miplib/data/iterators/fourier_shell_iterators.py
miplib/data/messages/__init__.py
miplib/data/messages/image_writer_wrappers.py
miplib/processing/__init__.py
miplib/processing/converters.py
miplib-1.0.6.dist-info/METADATA
miplib-1.0.6.dist-info/WHEEL
miplib-1.0.6.dist-info/entry_points.txt
miplib-1.0.6.dist-info/top_level.txt
miplib-1.0.6.dist-info/RECORD
