Metadata-Version: 2.1
Name: miplib
Version: 1.0.6
Summary: A Python software library for (optical) microscopy image restoration, reconstruction and analysis.
Home-page: UNKNOWN
Author: Sami Koho
Author-email: sami.koho@gmail.com
License: BSD
Download-URL: https://github.com/sakoho81/miplib/archive/v1.0.6.tar.gz
Platform: any
Classifier: Development Status :: 3 - Alpha
Classifier: Intended Audience :: Developers
Classifier: Topic :: Software Development :: Libraries :: Python Modules
Classifier: License :: OSI Approved :: BSD License
Classifier: Programming Language :: Python :: 3.6
Requires-Dist: numpy
Requires-Dist: scipy
Requires-Dist: h5py
Requires-Dist: SimpleITK
Requires-Dist: jpype1
Requires-Dist: matplotlib
Requires-Dist: pandas
Requires-Dist: pims
Requires-Dist: scikit-image
Requires-Dist: psf
